ragna_aws/__init__.py
ragna_aws/_s3.py
ragna_aws/_utils.py
ragna_aws/_version.py
ragna_aws/py.typed
ragna_aws/_bedrock/__init__.py
ragna_aws/_bedrock/ai21_labs.py
ragna_aws/_bedrock/amazon.py
ragna_aws/_bedrock/anthropic.py
ragna_aws/_bedrock/assistant.py
ragna_aws/_bedrock/cohere.py
ragna_aws/_bedrock/meta.py
ragna_aws-0.2.0.dist-info/LICENSE
ragna_aws-0.2.0.dist-info/METADATA
ragna_aws-0.2.0.dist-info/WHEEL
ragna_aws-0.2.0.dist-info/top_level.txt
ragna_aws-0.2.0.dist-info/RECORD
