Metadata-Version: 2.1
Name: ragna-aws
Version: 0.2.0
Summary: AWS extensions for Ragna
Author-email: Philip Meier <github.pmeier@posteo.de>
License: BSD 3-Clause License
Project-URL: Repository, https://github.com/pmeier/ragna-aws
Classifier: Development Status :: 4 - Beta
Classifier: Programming Language :: Python :: 3.9
Classifier: Programming Language :: Python :: 3.10
Classifier: Programming Language :: Python :: 3.11
Requires-Python: >=3.9
License-File: LICENSE
Requires-Dist: boto3 <2,>=1.28.57
Requires-Dist: botocore
Requires-Dist: ragna <0.3,>=0.2
